apacai/__init__.py
apacai/_apacai_scripts.py
apacai/apacai_object.py
apacai/apacai_response.py
apacai/api_requestor.py
apacai/api_resources/__init__.py
apacai/api_resources/abstract/__init__.py
apacai/api_resources/abstract/api_resource.py
apacai/api_resources/abstract/createable_api_resource.py
apacai/api_resources/abstract/deletable_api_resource.py
apacai/api_resources/abstract/engine_api_resource.py
apacai/api_resources/abstract/listable_api_resource.py
apacai/api_resources/abstract/nested_resource_class_methods.py
apacai/api_resources/abstract/updateable_api_resource.py
apacai/api_resources/audio.py
apacai/api_resources/chat_completion.py
apacai/api_resources/completion.py
apacai/api_resources/customer.py
apacai/api_resources/deployment.py
apacai/api_resources/edit.py
apacai/api_resources/embedding.py
apacai/api_resources/engine.py
apacai/api_resources/error_object.py
apacai/api_resources/experimental/__init__.py
apacai/api_resources/experimental/completion_config.py
apacai/api_resources/file.py
apacai/api_resources/fine_tune.py
apacai/api_resources/image.py
apacai/api_resources/model.py
apacai/api_resources/moderation.py
apacai/cli.py
apacai/datalib/__init__.py
apacai/datalib/common.py
apacai/datalib/numpy_helper.py
apacai/datalib/pandas_helper.py
apacai/embeddings_utils.py
apacai/error.py
apacai/object_classes.py
apacai/py.typed
apacai/tests/__init__.py
apacai/tests/asyncio/__init__.py
apacai/tests/asyncio/test_endpoints.py
apacai/tests/test_api_requestor.py
apacai/tests/test_endpoints.py
apacai/tests/test_exceptions.py
apacai/tests/test_file_cli.py
apacai/tests/test_long_examples_validator.py
apacai/tests/test_url_composition.py
apacai/tests/test_util.py
apacai/upload_progress.py
apacai/util.py
apacai/validators.py
apacai/version.py
apacai/wandb_logger.py
apacai-0.1.0.dist-info/LICENSE
apacai-0.1.0.dist-info/WHEEL
apacai-0.1.0.dist-info/METADATA
apacai-0.1.0.dist-info/RECORD
